google_form_prefiller/__init__.py
google_form_prefiller/google_form_prefiller.py
google_form_prefiller-0.0.2.dist-info/LICENSE
google_form_prefiller-0.0.2.dist-info/METADATA
google_form_prefiller-0.0.2.dist-info/WHEEL
google_form_prefiller-0.0.2.dist-info/entry_points.txt
google_form_prefiller-0.0.2.dist-info/top_level.txt
google_form_prefiller-0.0.2.dist-info/RECORD
