Metadata-Version: 2.1
Name: google-form-prefiller
Version: 0.0.2
Summary: Prefill Google forms from a YAML configuration file
Home-page: https://github.com/someone-stole-my-name/google-form-prefiller
Author: Christian Segundo
Author-email: chn2guevara@gmail.com
License: UNKNOWN
Project-URL: Bug Tracker, https://github.com/someone-stole-my-name/google-form-prefiller/issues
Platform: UNKNOWN
Classifier: Programming Language :: Python :: 3
Classifier: License :: OSI Approved :: MIT License
Classifier: Operating System :: OS Independent
Requires-Python: >=3.6
License-File: LICENSE
Requires-Dist: pyyaml
